hyperplane/__init__.py
hyperplane/cli/__init__.py
hyperplane/cli/dataset.py
hyperplane/cli/hyp.py
hyperplane/configuration/__init__.py
hyperplane/tests/__init__.py
hyp3-0.1.0.dist-info/WHEEL
hyp3-0.1.0.dist-info/entry_points.txt
hyp3-0.1.0.dist-info/METADATA
hyp3-0.1.0.dist-info/RECORD
